ado/__main__.py
ado/cli.py
ado/client.py
ado/config.py
ado/git_utils.py
ado/ui.py
ado_cli-0.0.5.dist-info/METADATA
ado_cli-0.0.5.dist-info/WHEEL
ado_cli-0.0.5.dist-info/entry_points.txt
ado_cli-0.0.5.dist-info/RECORD
