Metadata-Version: 2.4
Name: ado-cli
Version: 0.0.5
Summary: A GitHub CLI (gh) style interface for Azure DevOps Server (ado)
Author-email: Aaron Glover <aglove2189@gmail.com>
License: MIT
Keywords: ado,azure-devops,cli,devops,git
Classifier: Development Status :: 4 - Beta
Classifier: Intended Audience :: Developers
Classifier: License :: OSI Approved :: MIT License
Classifier: Programming Language :: Python :: 3
Classifier: Programming Language :: Python :: 3.8
Classifier: Programming Language :: Python :: 3.9
Classifier: Programming Language :: Python :: 3.10
Classifier: Programming Language :: Python :: 3.11
Classifier: Programming Language :: Python :: 3.12
Requires-Python: >=3.10
Requires-Dist: click>=8.3.1
Requires-Dist: httpx>=0.28.1
Requires-Dist: rich>=14.2.0
